src/__init__.py
src/estimators/__init__.py
src/estimators/estimator.py
src/estimators/kkt_estimator.py
src/helpers/__init__.py
src/models/__init__.py
src/models/ode_model.py
src/models/ode_model_base.py
src/solvers/__init__.py
tests/__init__.py
tests/test_estimator.py
ode_estimator-0.1.0.dist-info/LICENSE
ode_estimator-0.1.0.dist-info/METADATA
ode_estimator-0.1.0.dist-info/WHEEL
ode_estimator-0.1.0.dist-info/top_level.txt
ode_estimator-0.1.0.dist-info/RECORD
