Metadata-Version: 2.2
Name: ode-estimator
Version: 0.1.0
Summary: ODE Estimator is a project designed to model and estimate parameters of systems of ordinary differential equations (ODEs).
Home-page: https://github.com/NahomiB/ode-estimator
Author: Nahomi Bouza
Author-email: nahomi.bouza@gmail.com
Classifier: Programming Language :: Python :: 3
Classifier: License :: OSI Approved :: MIT License
Classifier: Operating System :: OS Independent
Requires-Python: >=3.6
License-File: LICENSE
Dynamic: author
Dynamic: author-email
Dynamic: classifier
Dynamic: description
Dynamic: description-content-type
Dynamic: home-page
Dynamic: requires-python
Dynamic: summary
